elasticsearch_dsl/__init__.py
elasticsearch_dsl/aggs.py
elasticsearch_dsl/analysis.py
elasticsearch_dsl/connections.py
elasticsearch_dsl/document.py
elasticsearch_dsl/exceptions.py
elasticsearch_dsl/faceted_search.py
elasticsearch_dsl/field.py
elasticsearch_dsl/function.py
elasticsearch_dsl/index.py
elasticsearch_dsl/mapping.py
elasticsearch_dsl/query.py
elasticsearch_dsl/search.py
elasticsearch_dsl/serializer.py
elasticsearch_dsl/update_by_query.py
elasticsearch_dsl/utils.py
elasticsearch_dsl/wrappers.py
elasticsearch_dsl/response/__init__.py
elasticsearch_dsl/response/aggs.py
elasticsearch_dsl/response/hit.py
elasticsearch_dsl_aq-8.0.1.dist-info/AUTHORS
elasticsearch_dsl_aq-8.0.1.dist-info/LICENSE
elasticsearch_dsl_aq-8.0.1.dist-info/METADATA
elasticsearch_dsl_aq-8.0.1.dist-info/WHEEL
elasticsearch_dsl_aq-8.0.1.dist-info/top_level.txt
elasticsearch_dsl_aq-8.0.1.dist-info/RECORD
