Metadata-Version: 2.1
Name: elasticsearch-dsl-aq
Version: 8.0.1
Summary: Python client for Elasticsearch
Home-page: https://github.com/accelq/elasticsearch-dsl-py
Author: accelq
Author-email: vivek.burman@accelq.com
Maintainer: accelq
Maintainer-email: vivek.burman@accelq.com
License: Apache-2.0
Classifier: Development Status :: 4 - Beta
Classifier: License :: OSI Approved :: Apache Software License
Classifier: Intended Audience :: Developers
Classifier: Operating System :: OS Independent
Classifier: Programming Language :: Python
Classifier: Programming Language :: Python :: 3
Classifier: Programming Language :: Python :: 3 :: Only
Classifier: Programming Language :: Python :: 3.6
Classifier: Programming Language :: Python :: 3.7
Classifier: Programming Language :: Python :: 3.8
Classifier: Programming Language :: Python :: 3.9
Classifier: Programming Language :: Python :: 3.10
Classifier: Programming Language :: Python :: 3.11
Classifier: Programming Language :: Python :: Implementation :: CPython
Classifier: Programming Language :: Python :: Implementation :: PyPy
Requires-Python: >=3.6
License-File: LICENSE
License-File: AUTHORS
Requires-Dist: python-dateutil
Requires-Dist: elasticsearch (>=7.0.0)
Provides-Extra: develop
Requires-Dist: pytest (>=3.0.0) ; extra == 'develop'
Requires-Dist: pytest-cov ; extra == 'develop'
Requires-Dist: pytest-mock (<3.0.0) ; extra == 'develop'
Requires-Dist: pytz ; extra == 'develop'
Requires-Dist: coverage (<5.0.0) ; extra == 'develop'
Requires-Dist: sphinx ; extra == 'develop'
Requires-Dist: sphinx-rtd-theme ; extra == 'develop'
